{
	"12512105": [
		{
			"description": "",
			"icon": "up",
			"xPosition": 146,
			"xTile": 125,
			"yPosition": 105,
			"yTile": 121
		},
		{
			"description": "Frost Dragons and Crystal Spiders",
			"icon": "red down",
			"xPosition": 105,
			"xTile": 125,
			"yPosition": 138,
			"yTile": 121
		}
	],
	"12512405": [
		{
			"description": "General Information and Creature Products",
			"icon": "!",
			"xPosition": 71,
			"xTile": 125,
			"yPosition": 156,
			"yTile": 124
		},
		{
			"description": "Weapons and Armor",
			"icon": "bag",
			"xPosition": 71,
			"xTile": 125,
			"yPosition": 137,
			"yTile": 124
		},
		{
			"description": "Food and Equipment",
			"icon": "bag",
			"xPosition": 57,
			"xTile": 125,
			"yPosition": 137,
			"yTile": 124
		},
		{
			"description": "Potions and Magic Store",
			"icon": "bag",
			"xPosition": 57,
			"xTile": 125,
			"yPosition": 156,
			"yTile": 124
		},
		{
			"description": "To the Bank and SpellsTrainers, Safe Trade Rooms and Mr Morris",
			"icon": "up",
			"xPosition": 74,
			"xTile": 125,
			"yPosition": 151,
			"yTile": 124
		},
		{
			"description": "To the Temple and Vocation Doors",
			"icon": "cross",
			"xPosition": 65,
			"xTile": 125,
			"yPosition": 144,
			"yTile": 124
		},
		{
			"description": "Ship to Main",
			"icon": "flag",
			"xPosition": 33,
			"xTile": 125,
			"yPosition": 130,
			"yTile": 124
		},
		{
			"description": "Druid's Gate",
			"icon": "red down",
			"xPosition": 64,
			"xTile": 125,
			"yPosition": 157,
			"yTile": 124
		},
		{
			"description": "Paladin's Gate",
			"icon": "red right",
			"xPosition": 75,
			"xTile": 125,
			"yPosition": 147,
			"yTile": 124
		},
		{
			"description": "Sorcerer's Gate",
			"icon": "red left",
			"xPosition": 55,
			"xTile": 125,
			"yPosition": 146,
			"yTile": 124
		},
		{
			"description": "Knight's Gate",
			"icon": "red up",
			"xPosition": 64,
			"xTile": 125,
			"yPosition": 136,
			"yTile": 124
		},
		{
			"description": "General Information and Creature Products",
			"icon": "!",
			"xPosition": 71,
			"xTile": 125,
			"yPosition": 156,
			"yTile": 124
		},
		{
			"description": "Weapons and Armor",
			"icon": "bag",
			"xPosition": 71,
			"xTile": 125,
			"yPosition": 137,
			"yTile": 124
		},
		{
			"description": "Food and Equipment",
			"icon": "bag",
			"xPosition": 57,
			"xTile": 125,
			"yPosition": 137,
			"yTile": 124
		},
		{
			"description": "Potions and Magic Store",
			"icon": "bag",
			"xPosition": 57,
			"xTile": 125,
			"yPosition": 156,
			"yTile": 124
		},
		{
			"description": "To the Bank and SpellsTrainers, Safe Trade Rooms and Mr Morris",
			"icon": "up",
			"xPosition": 74,
			"xTile": 125,
			"yPosition": 151,
			"yTile": 124
		},
		{
			"description": "To the Temple and Vocation Doors",
			"icon": "cross",
			"xPosition": 65,
			"xTile": 125,
			"yPosition": 144,
			"yTile": 124
		},
		{
			"description": "Ship to Main",
			"icon": "flag",
			"xPosition": 33,
			"xTile": 125,
			"yPosition": 130,
			"yTile": 124
		},
		{
			"description": "Druid's Gate",
			"icon": "red down",
			"xPosition": 64,
			"xTile": 125,
			"yPosition": 157,
			"yTile": 124
		},
		{
			"description": "Paladin's Gate",
			"icon": "red right",
			"xPosition": 75,
			"xTile": 125,
			"yPosition": 147,
			"yTile": 124
		},
		{
			"description": "Sorcerer's Gate",
			"icon": "red left",
			"xPosition": 55,
			"xTile": 125,
			"yPosition": 146,
			"yTile": 124
		},
		{
			"description": "Knight's Gate",
			"icon": "red up",
			"xPosition": 64,
			"xTile": 125,
			"yPosition": 136,
			"yTile": 124
		},
		{
			"description": "General Information and Creature Products",
			"icon": "!",
			"xPosition": 71,
			"xTile": 125,
			"yPosition": 156,
			"yTile": 124
		},
		{
			"description": "Weapons and Armor",
			"icon": "bag",
			"xPosition": 71,
			"xTile": 125,
			"yPosition": 137,
			"yTile": 124
		},
		{
			"description": "Food and Equipment",
			"icon": "bag",
			"xPosition": 57,
			"xTile": 125,
			"yPosition": 137,
			"yTile": 124
		},
		{
			"description": "Potions and Magic Store",
			"icon": "bag",
			"xPosition": 57,
			"xTile": 125,
			"yPosition": 156,
			"yTile": 124
		},
		{
			"description": "To the Bank and SpellsTrainers, Safe Trade Rooms and Mr Morris",
			"icon": "up",
			"xPosition": 74,
			"xTile": 125,
			"yPosition": 151,
			"yTile": 124
		},
		{
			"description": "To the Temple and Vocation Doors",
			"icon": "cross",
			"xPosition": 65,
			"xTile": 125,
			"yPosition": 144,
			"yTile": 124
		},
		{
			"description": "Ship to the Mainland",
			"icon": "flag",
			"xPosition": 33,
			"xTile": 125,
			"yPosition": 130,
			"yTile": 124
		},
		{
			"description": "Druid's Gate",
			"icon": "red down",
			"xPosition": 64,
			"xTile": 125,
			"yPosition": 157,
			"yTile": 124
		},
		{
			"description": "Paladin's Gate",
			"icon": "red right",
			"xPosition": 75,
			"xTile": 125,
			"yPosition": 147,
			"yTile": 124
		},
		{
			"description": "Sorcerer's Gate",
			"icon": "red left",
			"xPosition": 55,
			"xTile": 125,
			"yPosition": 146,
			"yTile": 124
		},
		{
			"description": "Knight's Gate",
			"icon": "red up",
			"xPosition": 64,
			"xTile": 125,
			"yPosition": 136,
			"yTile": 124
		},
		{
			"description": "General Information and Creature Products",
			"icon": "!",
			"xPosition": 71,
			"xTile": 125,
			"yPosition": 156,
			"yTile": 124
		},
		{
			"description": "Weapons and Armor",
			"icon": "bag",
			"xPosition": 71,
			"xTile": 125,
			"yPosition": 137,
			"yTile": 124
		},
		{
			"description": "Food and Equipment",
			"icon": "bag",
			"xPosition": 57,
			"xTile": 125,
			"yPosition": 137,
			"yTile": 124
		},
		{
			"description": "Potions and Magic Store",
			"icon": "bag",
			"xPosition": 57,
			"xTile": 125,
			"yPosition": 156,
			"yTile": 124
		},
		{
			"description": "To the Bank and SpellsTrainers, Safe Trade Rooms and Mr Morris",
			"icon": "up",
			"xPosition": 74,
			"xTile": 125,
			"yPosition": 151,
			"yTile": 124
		},
		{
			"description": "To the Temple and Vocation Doors",
			"icon": "cross",
			"xPosition": 65,
			"xTile": 125,
			"yPosition": 144,
			"yTile": 124
		},
		{
			"description": "Ship to the Mainland",
			"icon": "flag",
			"xPosition": 33,
			"xTile": 125,
			"yPosition": 130,
			"yTile": 124
		},
		{
			"description": "Druid's Gate",
			"icon": "red down",
			"xPosition": 64,
			"xTile": 125,
			"yPosition": 157,
			"yTile": 124
		},
		{
			"description": "Paladin's Gate",
			"icon": "red right",
			"xPosition": 75,
			"xTile": 125,
			"yPosition": 147,
			"yTile": 124
		},
		{
			"description": "Sorcerer's Gate",
			"icon": "red left",
			"xPosition": 55,
			"xTile": 125,
			"yPosition": 146,
			"yTile": 124
		},
		{
			"description": "Knight's Gate",
			"icon": "red up",
			"xPosition": 64,
			"xTile": 125,
			"yPosition": 136,
			"yTile": 124
		},
		{
			"description": "General Information and Creature Products",
			"icon": "!",
			"xPosition": 71,
			"xTile": 125,
			"yPosition": 156,
			"yTile": 124
		},
		{
			"description": "Weapons and Armor",
			"icon": "bag",
			"xPosition": 71,
			"xTile": 125,
			"yPosition": 137,
			"yTile": 124
		},
		{
			"description": "Food and Equipment",
			"icon": "bag",
			"xPosition": 57,
			"xTile": 125,
			"yPosition": 137,
			"yTile": 124
		},
		{
			"description": "Potions and Magic Store",
			"icon": "bag",
			"xPosition": 57,
			"xTile": 125,
			"yPosition": 156,
			"yTile": 124
		},
		{
			"description": "To the Bank and SpellsTrainers, Safe Trade Rooms and Mr Morris",
			"icon": "up",
			"xPosition": 74,
			"xTile": 125,
			"yPosition": 151,
			"yTile": 124
		},
		{
			"description": "To the Temple and Vocation Doors",
			"icon": "cross",
			"xPosition": 65,
			"xTile": 125,
			"yPosition": 144,
			"yTile": 124
		},
		{
			"description": "Ship to the Mainland",
			"icon": "flag",
			"xPosition": 33,
			"xTile": 125,
			"yPosition": 130,
			"yTile": 124
		},
		{
			"description": "Druid's Gate",
			"icon": "red down",
			"xPosition": 64,
			"xTile": 125,
			"yPosition": 157,
			"yTile": 124
		},
		{
			"description": "Paladin's Gate",
			"icon": "red right",
			"xPosition": 75,
			"xTile": 125,
			"yPosition": 147,
			"yTile": 124
		},
		{
			"description": "Sorcerer's Gate",
			"icon": "red left",
			"xPosition": 55,
			"xTile": 125,
			"yPosition": 146,
			"yTile": 124
		},
		{
			"description": "Knight's Gate",
			"icon": "red up",
			"xPosition": 64,
			"xTile": 125,
			"yPosition": 136,
			"yTile": 124
		}
	],
	"12512705": [
		{
			"description": "",
			"icon": "up",
			"xPosition": 66,
			"xTile": 125,
			"yPosition": 112,
			"yTile": 127
		},
		{
			"description": "",
			"icon": "down",
			"xPosition": 48,
			"xTile": 125,
			"yPosition": 97,
			"yTile": 127
		}
	],
	"12712405": [
		{
			"description": "Magic Store",
			"icon": "star",
			"xPosition": 118,
			"xTile": 127,
			"yPosition": 184,
			"yTile": 124
		}
	],
	"12812205": [
		{
			"description": "Offline Training",
			"icon": "sword",
			"xPosition": 19,
			"xTile": 128,
			"yPosition": 17,
			"yTile": 122
		}
	],
	"12812505": [
		{
			"description": "Boozer",
			"icon": "mouth",
			"xPosition": 153,
			"xTile": 128,
			"yPosition": 68,
			"yTile": 125
		},
		{
			"description": "Boozer",
			"icon": "mouth",
			"xPosition": 153,
			"xTile": 128,
			"yPosition": 68,
			"yTile": 125
		},
		{
			"description": "Boozer",
			"icon": "mouth",
			"xPosition": 153,
			"xTile": 128,
			"yPosition": 68,
			"yTile": 125
		},
		{
			"description": "Boozer",
			"icon": "mouth",
			"xPosition": 153,
			"xTile": 128,
			"yPosition": 68,
			"yTile": 125
		},
		{
			"description": "Boozer",
			"icon": "mouth",
			"xPosition": 153,
			"xTile": 128,
			"yPosition": 68,
			"yTile": 125
		},
		{
			"description": "Boozer",
			"icon": "mouth",
			"xPosition": 153,
			"xTile": 128,
			"yPosition": 68,
			"yTile": 125
		},
		{
			"description": "Boozer",
			"icon": "mouth",
			"xPosition": 153,
			"xTile": 128,
			"yPosition": 68,
			"yTile": 125
		}
	],
	"12912105": [
		{
			"description": "Silver Ewer (Daily Spawn)",
			"icon": "bag",
			"xPosition": 67,
			"xTile": 129,
			"yPosition": 135,
			"yTile": 121
		}
	],
	"13112405": [
		{
			"description": "Barazbaz",
			"icon": "!",
			"xPosition": 114,
			"xTile": 131,
			"yPosition": 140,
			"yTile": 124
		},
		{
			"description": "Marvin",
			"icon": "!",
			"xPosition": 126,
			"xTile": 131,
			"yPosition": 134,
			"yTile": 124
		},
		{
			"description": "Barazbaz",
			"icon": "!",
			"xPosition": 114,
			"xTile": 131,
			"yPosition": 140,
			"yTile": 124
		},
		{
			"description": "Marvin",
			"icon": "!",
			"xPosition": 126,
			"xTile": 131,
			"yPosition": 134,
			"yTile": 124
		}
	]
}
